fpga/blinky/src/blink.vhdl
-- Import the IEEE standard logic library (provides std_logic types)
library IEEE;
-- Use the std_logic_1164 package for digital logic types ('0', '1', 'Z', etc.)
use IEEE.STD_LOGIC_1164.ALL;
-- Use the numeric_std package for arithmetic operations on std_logic_vector
use IEEE.NUMERIC_STD.ALL;

-- Entity declaration: defines the external interface (inputs/outputs) of the module
entity blinky is
    -- Generics are like compile-time constants that can be overridden
    generic (
        CLK_FREQ : integer := 12000000;  -- Clock frequency in Hz (12 MHz on ECP5 Versa board)
        BLINK_FREQ : integer := 1        -- Desired blink rate in Hz (1 Hz = 1 blink per second)
    );
    -- Ports are the actual input/output pins
    port (
        clk : in std_logic;                       -- Clock input from FPGA oscillator
        rst : in std_logic;                       -- Reset input (active high - '1' = reset)
        led : out std_logic_vector(7 downto 0)    -- 8-bit output bus for LEDs (7 down to 0)
    );
end blinky;

-- Architecture: describes the internal behavior/implementation of the entity
architecture rtl of blinky is
    -- Calculate how many clock cycles to count before toggling LED
    -- Divide by 2 because we toggle (not full cycle), so 6M counts = 0.5 sec
    constant MAX_COUNT : integer := CLK_FREQ / (2 * BLINK_FREQ);

    -- Internal signal to count clock cycles (0 to 6,000,000)
    -- The "range" constraint helps synthesis optimize the counter size
    signal counter : integer range 0 to MAX_COUNT := 0;

    -- Internal signal to hold current LED state (on or off)
    -- Initialized to '0' (LED off at startup)
    signal led_state : std_logic := '0';
    signal led_state_offset : std_logic := '0';
begin

    -- Process: a sequential block that executes when any signal in sensitivity list changes
    -- Sensitivity list: (clk, rst) means run this process when clk OR rst changes
    process(clk, rst)
    begin
        -- Check reset first (highest priority) - this is "asynchronous reset"
        -- When rst is '1', immediately reset counter and LED regardless of clock
        if rst = '1' then
            counter <= 0;           -- Reset counter to 0
            led_state <= '0';       -- Turn LED off
            led_state_offset <= '0';       -- Turn LED off

        -- If not resetting, check for rising edge of clock (0 -> 1 transition)
        -- This makes it a "synchronous" design - changes only happen on clock edge
        elsif falling_edge(clk) then 
            if counter = (MAX_COUNT / 2) then
                led_state_offset <= not led_state_offset;  -- Toggle LED state (0->1 or 1->0)
            end if;
        elsif rising_edge(clk) then

            -- Check if we've counted up to our target (6,000,000 - 1)
            -- We use MAX_COUNT - 1 because we start counting from 0
            if counter = MAX_COUNT - 1 then
                counter <= 0;                -- Reset counter back to 0
                led_state <= not led_state;  -- Toggle LED state (0->1 or 1->0)

            -- If we haven't reached the target yet, keep counting
            else
                counter <= counter + 1;      -- Increment counter by 1
            end if;
        end if;
    end process;

    -- Concurrent signal assignments (happen continuously, not just on clock edges)
    -- Drive LED0 with the blinking led_state signal
    led(0) <= led_state;
    led(1) <= not led_state;
    led(2) <= led_state;
    led(3) <= led_state_offset;

    -- Drive all other LEDs (7 down to 1) to '0' (off)
    -- The "(others => '0')" syntax means "set all remaining bits to 0"
    led(7 downto 4) <= (others => '0');

end rtl;

fpga/blinky/sim/test.vhdl
-- Import the IEEE standard logic library (provides std_logic types)
library IEEE;
-- Use the std_logic_1164 package for digital logic types
use IEEE.STD_LOGIC_1164.ALL;
-- Use the numeric_std package for arithmetic operations
use IEEE.NUMERIC_STD.ALL;

-- Testbench entity has NO ports - it's a self-contained test environment
-- The "_tb" suffix is a common naming convention for testbenches
entity blinky_tb is
end blinky_tb;

-- Architecture for the testbench - describes the test setup
architecture sim of blinky_tb is

    -- Component declaration: describes the interface of the module we're testing
    -- This must match the entity we declared in blink.vhdl
    component blinky is
        generic (
            CLK_FREQ : integer := 12000000;    -- Default clock frequency
            BLINK_FREQ : integer := 1          -- Default blink frequency
        );
        port (
            clk : in std_logic;                       -- Clock input
            rst : in std_logic;                       -- Reset input
            led : out std_logic_vector(7 downto 0)    -- 8-bit LED output (UPDATED!)
        );
    end component;

    -- Testbench signals: these connect to the component under test
    -- We initialize them to known values for simulation
    signal clk : std_logic := '0';                   -- Clock signal, starts at '0'
    signal rst : std_logic := '0';                   -- Reset signal, starts at '0' (not reset)
    signal led : std_logic_vector(7 downto 0);       -- 8-bit LED output (UPDATED!)

    -- Clock period definition for simulation
    -- Real hardware uses 12 MHz, but we can use any period for simulation
    constant CLK_PERIOD : time := 83.33 ns;  -- Period for ~12 MHz (1/12MHz = 83.33ns)

    -- For simulation, we use MUCH faster frequencies so tests don't take forever!
    -- Real hardware: 12,000,000 Hz clock, 1 Hz blink = 12 million cycles per toggle
    -- Simulation: 1,000 Hz clock, 10 Hz blink = 50 cycles per toggle (much faster!)
    constant SIM_CLK_FREQ : integer := 1000;   -- 1 kHz simulated clock
    constant SIM_BLINK_FREQ : integer := 100;   -- 10 Hz simulated blink rate

    -- Signal to stop the clock generation when simulation is done
    signal sim_done : boolean := false;

begin

    -- Instantiate the Unit Under Test (UUT) - this creates an instance of our blinky module
    -- "uut" is the instance name (common abbreviation for "Unit Under Test")
    uut: blinky
        -- Generic map: override the default generic values
        -- This lets us use fast simulation frequencies instead of real hardware frequencies
        generic map (
            CLK_FREQ => SIM_CLK_FREQ,        -- Use 1 kHz instead of 12 MHz
            BLINK_FREQ => SIM_BLINK_FREQ     -- Use 10 Hz instead of 1 Hz
        )
        -- Port map: connect testbench signals to component ports
        -- Format is: component_port => testbench_signal
        port map (
            clk => clk,    -- Connect component's clk port to testbench's clk signal
            rst => rst,    -- Connect component's rst port to testbench's rst signal
            led => led     -- Connect component's led port to testbench's led signal
        );

    -- Clock generation process: creates a continuous square wave
    -- This process runs concurrently with other processes
    clk_process: process
    begin
        -- Loop forever (or until sim_done becomes true)
        while not sim_done loop
            clk <= '0';                -- Set clock low
            wait for CLK_PERIOD / 2;   -- Wait for half a period (41.67 ns)
            clk <= '1';                -- Set clock high
            wait for CLK_PERIOD / 2;   -- Wait for half a period (41.67 ns)
            -- This creates: __--__--__--  (square wave with 83.33ns period)
        end loop;
        wait;  -- Stop this process when sim_done is true
    end process;

    -- Stimulus process: applies test inputs to the UUT
    -- This is where we define our test sequence
    stim_process: process
    begin
        -- Test sequence starts here

        -- 1. Apply reset
        rst <= '1';           -- Assert reset (active high)
        wait for 100 ns;      -- Hold reset for 100 nanoseconds
        rst <= '0';           -- De-assert reset (release)

        -- 2. Let the design run and observe LED blinking
        -- With SIM_BLINK_FREQ = 10 Hz, LED should toggle every 100ms
        -- We'll run for 500ms to see ~5 toggles (2.5 full blink cycles)
        wait for 500 ms;

        -- 3. End the simulation
        sim_done <= true;     -- Signal clock process to stop

        -- Report message (shows in simulator console)
        report "Simulation completed successfully!";
        wait;  -- Stop this process (required at end of testbench)
    end process;

    -- Monitor process: watches for changes on the LED signal
    -- Sensitivity list (led) means this runs whenever 'led' changes
    -- This is optional but helpful for debugging
    monitor: process(led)
    begin
        -- Print a message every time LED changes
        -- 'image converts the value to a string for printing
        -- 'now' is the current simulation time
        report "LED(0) changed to: " & std_logic'image(led(0)) & " at time " & time'image(now);
    end process;

end sim;

fpga/blinky/sim/blinky_tb.vcd
$date
  Sat Oct 18 19:54:27 2025
$end
$version
  GHDL v0
$end
$timescale
  1 fs
$end
$scope module standard $end
$upscope $end
$scope module textio $end
$upscope $end
$scope module std_logic_1164 $end
$upscope $end
$scope module numeric_std $end
$upscope $end
$scope module blinky_tb $end
$var reg 1 ! clk $end
$var reg 1 " rst $end
$var reg 8 # led[7:0] $end
$var reg 1 $ sim_done $end
$scope module uut $end
$var reg 1 % clk $end
$var reg 1 & rst $end
$var reg 8 ' led[7:0] $end
$var integer 32 ( counter $end
$var reg 1 ) led_state $end
$var reg 1 * led_state_offset $end
$upscope $end
$upscope $end
$enddefinitions $end
#0
0!
1"
b00000010 #
0$
0%
1&
b00000010 '
b0 (
0)
0*
#41665000
1!
1%
#83330000
0!
0%
#100000000
0"
0&
#124995000
1!
1%
b1 (
#166660000
0!
0%
#208325000
1!
1%
b10 (
#249990000
0!
b00001010 #
0%
b00001010 '
1*
#291655000
1!
1%
b11 (
#333320000
0!
0%
#374985000
1!
1%
b100 (
#416650000
0!
0%
#458315000
1!
b00001101 #
1%
b00001101 '
b0 (
1)
#499980000
0!
0%
#541645000
1!
1%
b1 (
#583310000
0!
0%
#624975000
1!
1%
b10 (
#666640000
0!
b00000101 #
0%
b00000101 '
0*
#708305000
1!
1%
b11 (
#749970000
0!
0%
#791635000
1!
1%
b100 (
#833300000
0!
0%
#874965000
1!
b00000010 #
1%
b00000010 '
b0 (
0)
#916630000
0!
0%
#958295000
1!
1%
b1 (
#999960000
0!
0%
#1041625000
1!
1%
b10 (
#1083290000
0!
b00001010 #
0%
b00001010 '
1*
#1124955000
1!
1%
b11 (
#1166620000
0!
0%
#1208285000
1!
1%
b100 (
#1249950000
0!
0%
#1291615000
1!
b00001101 #
1%
b00001101 '
b0 (
1)
#1333280000
0!
0%
#1374945000
1!
1%
b1 (
#1416610000
0!
0%
#1458275000
1!
1%
b10 (
#1499940000
0!
b00000101 #
0%
b00000101 '
0*
#1541605000
1!
1%
b11 (
#1583270000
0!
0%
#1624935000
1!
1%
b100 (
#1666600000
0!
0%
#1708265000
1!
b00000010 #
1%
b00000010 '
b0 (
0)
#1749930000
0!
0%
#1791595000
1!
1%
b1 (
#1833260000
0!
0%
#1874925000
1!
1%
b10 (
#1916590000
0!
b00001010 #
0%
b00001010 '
1*
#1958255000
1!
1%
b11 (
#1999920000
0!
0%
#2041585000
1!
1%
b100 (
#2083250000
0!
0%
#2124915000
1!
b00001101 #
1%
b00001101 '
b0 (
1)
#2166580000
0!
0%
#2208245000
1!
1%
b1 (
#2249910000
0!
0%
#2291575000
1!
1%
b10 (
#2333240000
0!
b00000101 #
0%
b00000101 '
0*
#2374905000
1!
1%
b11 (
#2416570000
0!
0%
#2458235000
1!
1%
b100 (
#2499900000
0!
0%
#2541565000
1!
b00000010 #
1%
b00000010 '
b0 (
0)
#2583230000
0!
0%
#2624895000
1!
1%
b1 (
#2666560000
0!
0%
#2708225000
1!
1%
b10 (
#2749890000
0!
b00001010 #
0%
b00001010 '
1*
#2791555000
1!
1%
b11 (
#2833220000
0!
0%
#2874885000
1!
1%
b100 (
#2916550000
0!
0%
#2958215000
1!
b00001101 #
1%
b00001101 '
b0 (
1)
#2999880000
0!
0%
#3041545000
1!
1%
b1 (
#3083210000
0!
0%
#3124875000
1!
1%
b10 (
#3166540000
0!
b00000101 #
0%
b00000101 '
0*
#3208205000
1!
1%
b11 (
#3249870000
0!
0%
#3291535000
1!
1%
b100 (
#3333200000
0!
0%
#3374865000
1!
b00000010 #
1%
b00000010 '
b0 (
0)
#3416530000
0!
0%
#3458195000
1!
1%
b1 (
#3499860000
0!
0%
#3541525000
1!
1%
b10 (
#3583190000
0!
b00001010 #
0%
b00001010 '
1*
#3624855000
1!
1%
b11 (
#3666520000
0!
0%
#3708185000
1!
1%
b100 (
#3749850000
0!
0%
#3791515000
1!
b00001101 #
1%
b00001101 '
b0 (
1)
#3833180000
0!
0%
#3874845000
1!
1%
b1 (
#3916510000
0!
0%
#3958175000
1!
1%
b10 (
#3999840000
0!
b00000101 #
0%
b00000101 '
0*
#4041505000
1!
1%
b11 (
#4083170000
0!
0%
#4124835000
1!
1%
b100 (
#4166500000
0!
0%
#4208165000
1!
b00000010 #
1%
b00000010 '
b0 (
0)
#4249830000
0!
0%
#4291495000
1!
1%
b1 (
#4333160000
0!
0%
#4374825000
1!
1%
b10 (
#4416490000
0!
b00001010 #
0%
b00001010 '
1*
#4458155000
1!
1%
b11 (
#4499820000
0!
0%
#4541485000
1!
1%
b100 (
#4583150000
0!
0%
#4624815000
1!
b00001101 #
1%
b00001101 '
b0 (
1)
#4666480000
0!
0%
#4708145000
1!
1%
b1 (
#4749810000
0!
0%
#4791475000
1!
1%
b10 (
#4833140000
0!
b00000101 #
0%
b00000101 '
0*
#4874805000
1!
1%
b11 (
#4916470000
0!
0%
#4958135000
1!
1%
b100 (
#4999800000
0!
0%
#5041465000
1!
b00000010 #
1%
b00000010 '
b0 (
0)
#5083130000
0!
0%
#5124795000
1!
1%
b1 (
#5166460000
0!
0%
#5208125000
1!
1%
b10 (
#5249790000
0!
b00001010 #
0%
b00001010 '
1*
#5291455000
1!
1%
b11 (
#5333120000
0!
0%
#5374785000
1!
1%
b100 (
#5416450000
0!
0%
#5458115000
1!
b00001101 #
1%
b00001101 '
b0 (
1)
#5499780000
0!
0%
#5541445000
1!
1%
b1 (
#5583110000
0!
0%
#5624775000
1!
1%
b10 (
#5666440000
0!
b00000101 #
0%
b00000101 '
0*
#5708105000
1!
1%
b11 (
#5749770000
0!
0%
#5791435000
1!
1%
b100 (
#5833100000
0!
0%
#5874765000
1!
b00000010 #
1%
b00000010 '
b0 (
0)
#5916430000
0!
0%
#5958095000
1!
1%
b1 (
#5999760000
0!
0%
#6041425000
1!
1%
b10 (
#6083090000
0!
b00001010 #
0%
b00001010 '
1*
#6124755000
1!
1%
b11 (
#6166420000
0!
0%
#6208085000
1!
1%
b100 (
#6249750000
0!
0%
#6291415000
1!
b00001101 #
1%
b00001101 '
b0 (
1)
#6333080000
0!
0%
#6374745000
1!
1%
b1 (
#6416410000
0!
0%
#6458075000
1!
1%
b10 (
#6499740000
0!
b00000101 #
0%
b00000101 '
0*
#6541405000
1!
1%
b11 (
#6583070000
0!
0%
#6624735000
1!
1%
b100 (
#6666400000
0!
0%
#6708065000
1!
b00000010 #
1%
b00000010 '
b0 (
0)
#6749730000
0!
0%
#6791395000
1!
1%
b1 (
#6833060000
0!
0%
#6874725000
1!
1%
b10 (
#6916390000
0!
b00001010 #
0%
b00001010 '
1*
#6958055000
1!
1%
b11 (
#6999720000
0!
0%
#7041385000
1!
1%
b100 (
#7083050000
0!
0%
#7124715000
1!
b00001101 #
1%
b00001101 '
b0 (
1)
#7166380000
0!
0%
#7208045000
1!
1%
b1 (
#7249710000
0!
0%
#7291375000
1!
1%
b10 (
#7333040000
0!
b00000101 #
0%
b00000101 '
0*
#7374705000
1!
1%
b11 (
#7416370000
0!
0%
#7458035000
1!
1%
b100 (
#7499700000
0!
0%
#7541365000
1!
b00000010 #
1%
b00000010 '
b0 (
0)
#7583030000
0!
0%
#7624695000
1!
1%
b1 (
#7666360000
0!
0%
#7708025000
1!
1%
b10 (
#7749690000
0!
b00001010 #
0%
b00001010 '
1*
#7791355000
1!
1%
b11 (
#7833020000
0!
0%
#7874685000
1!
1%
b100 (
#7916350000
0!
0%
#7958015000
1!
b00001101 #
1%
b00001101 '
b0 (
1)
#7999680000
0!
0%
#8041345000
1!
1%
b1 (
#8083010000
0!
0%
#8124675000
1!
1%
b10 (
#8166340000
0!
b00000101 #
0%
b00000101 '
0*
#8208005000
1!
1%
b11 (
#8249670000
0!
0%
#8291335000
1!
1%
b100 (
#8333000000
0!
0%
#8374665000
1!
b00000010 #
1%
b00000010 '
b0 (
0)
#8416330000
0!
0%
#8457995000
1!
1%
b1 (
#8499660000
0!
0%
#8541325000
1!
1%
b10 (
#8582990000
0!
b00001010 #
0%
b00001010 '
1*
#8624655000
1!
1%
b11 (
#8666320000
0!
0%
#8707985000
1!
1%
b100 (
#8749650000
0!
0%
#8791315000
1!
b00001101 #
1%
b00001101 '
b0 (
1)
#8832980000
0!
0%
#8874645000
1!
1%
b1 (
#8916310000
0!
0%
#8957975000
1!
1%
b10 (
#8999640000
0!
b00000101 #
0%
b00000101 '
0*
#9041305000
1!
1%
b11 (
#9082970000
0!
0%
#9124635000
1!
1%
b100 (
#9166300000
0!
0%
#9207965000
1!
b00000010 #
1%
b00000010 '
b0 (
0)
#9249630000
0!
0%
#9291295000
1!
1%
b1 (
#9332960000
0!
0%
#9374625000
1!
1%
b10 (
#9416290000
0!
b00001010 #
0%
b00001010 '
1*
#9457955000
1!
1%
b11 (
#9499620000
0!
0%
#9541285000
1!
1%
b100 (
#9582950000
0!
0%
#9624615000
1!
b00001101 #
1%
b00001101 '
b0 (
1)
#9666280000
0!
0%
#9707945000
1!
1%
b1 (
#9749610000
0!
0%
#9791275000
1!
1%
b10 (
#9832940000
0!
b00000101 #
0%
b00000101 '
0*
#9874605000
1!
1%
b11 (
#9916270000
0!
0%
#9957935000
1!
1%
b100 (
#9999600000
0!
0%
#10041265000
1!
b00000010 #
1%
b00000010 '
b0 (
0)
#10082930000
0!
0%
#10124595000
1!
1%
b1 (
#10166260000
0!
0%
#10207925000
1!
1%
b10 (
#10249590000
0!
b00001010 #
0%
b00001010 '
1*
#10291255000
1!
1%
b11 (
#10332920000
0!
0%
#10374585000
1!
1%
b100 (
#10416250000
0!
0%
#10457915000
1!
b00001101 #
1%
b00001101 '
b0 (
1)
#10499580000
0!
0%
#10541245000
1!
1%
b1 (
#10582910000
0!
0%
#10624575000
1!
1%
b10 (
#10666240000
0!
b00000101 #
0%
b00000101 '
0*
#10707905000
1!
1%
b11 (
#10749570000
0!
0%
#10791235000
1!
1%
b100 (
#10832900000
0!
0%
#10874565000
1!
b00000010 #
1%
b00000010 '
b0 (
0)
#10916230000
0!
0%
#10957895000
1!
1%
b1 (
#10999560000
0!
0%
#11041225000
1!
1%
b10 (
#11082890000
0!
b00001010 #
0%
b00001010 '
1*
#11124555000
1!
1%
b11 (
#11166220000
0!
0%
#11207885000
1!
1%
b100 (
#11249550000
0!
0%
#11291215000
1!
b00001101 #
1%
b00001101 '
b0 (
1)
#11332880000
0!
0%
#11374545000
1!
1%
b1 (
#11416210000
0!
0%
#11457875000
1!
1%
b10 (
#11499540000
0!
b00000101 #
0%
b00000101 '
0*
#11541205000
1!
1%
b11 (
#11582870000
0!
0%
#11624535000
1!
1%
b100 (
#11666200000
0!
0%
#11707865000
1!
b00000010 #
1%
b00000010 '
b0 (
0)
#11749530000
0!
0%
#11791195000
1!
1%
b1 (
#11832860000
0!
0%
#11874525000
1!
1%
b10 (
#11916190000
0!
b00001010 #
0%
b00001010 '
1*
#11957855000
1!
1%
b11 (
#11999520000
0!
0%
#12041185000
1!
1%
b100 (
#12082850000
0!
0%
#12124515000
1!
b00001101 #
1%
b00001101 '
b0 (
1)
#12166180000
0!
0%
#12207845000
1!
1%
b1 (
#12249510000
0!
0%
#12291175000
1!
1%
b10 (
#12332840000
0!
b00000101 #
0%
b00000101 '
0*
#12374505000
1!
1%
b11 (
#12416170000
0!
0%
#12457835000
1!
1%
b100 (
#12499500000
0!
0%
#12541165000
1!
b00000010 #
1%
b00000010 '
b0 (
0)
#12582830000
0!
0%
#12624495000
1!
1%
b1 (
#12666160000
0!
0%
#12707825000
1!
1%
b10 (
#12749490000
0!
b00001010 #
0%
b00001010 '
1*
#12791155000
1!
1%
b11 (
#12832820000
0!
0%
#12874485000
1!
1%
b100 (
#12916150000
0!
0%
#12957815000
1!
b00001101 #
1%
b00001101 '
b0 (
1)
#12999480000
0!
0%
#13041145000
1!
1%
b1 (
#13082810000
0!
0%
#13124475000
1!
1%
b10 (
#13166140000
0!
b00000101 #
0%
b00000101 '
0*
#13207805000
1!
1%
b11 (
#13249470000
0!
0%
#13291135000
1!
1%
b100 (
#13332800000
0!
0%
#13374465000
1!
b00000010 #
1%
b00000010 '
b0 (
0)
#13416130000
0!
0%
#13457795000
1!
1%
b1 (
#13499460000
0!
0%
#13541125000
1!
1%
b10 (
#13582790000
0!
b00001010 #
0%
b00001010 '
1*
#13624455000
1!
1%
b11 (
#13666120000
0!
0%
#13707785000
1!
1%
b100 (
#13749450000
0!
0%
#13791115000
1!
b00001101 #
1%
b00001101 '
b0 (
1)
#13832780000
0!
0%
#13874445000
1!
1%
b1 (
#13916110000
0!
0%
#13957775000
1!
1%
b10 (
#13999440000
0!
b00000101 #
0%
b00000101 '
0*
#14041105000
1!
1%
b11 (
#14082770000
0!
0%
#14124435000
1!
1%
b100 (
#14166100000
0!
0%
#14207765000
1!
b00000010 #
1%
b00000010 '
b0 (
0)
#14249430000
0!
0%
#14291095000
1!
1%
b1 (
#14332760000
0!
0%
#14374425000
1!
1%
b10 (
#14416090000
0!
b00001010 #
0%
b00001010 '
1*
#14457755000
1!
1%
b11 (
#14499420000
0!
0%
#14541085000
1!
1%
b100 (
#14582750000
0!
0%
#14624415000
1!
b00001101 #
1%
b00001101 '
b0 (
1)
#14666080000
0!
0%
#14707745000
1!
1%
b1 (
#14749410000
0!
0%
#14791075000
1!
1%
b10 (
#14832740000
0!
b00000101 #
0%
b00000101 '
0*
#14874405000
1!
1%
b11 (
#14916070000
0!
0%
#14957735000
1!
1%
b100 (
#14999400000
0!
0%
#15041065000
1!
b00000010 #
1%
b00000010 '
b0 (
0)
#15082730000
0!
0%
#15124395000
1!
1%
b1 (
#15166060000
0!
0%
#15207725000
1!
1%
b10 (
#15249390000
0!
b00001010 #
0%
b00001010 '
1*
#15291055000
1!
1%
b11 (
#15332720000
0!
0%
#15374385000
1!
1%
b100 (
#15416050000
0!
0%
#15457715000
1!
b00001101 #
1%
b00001101 '
b0 (
1)
#15499380000
0!
0%
#15541045000
1!
1%
b1 (
#15582710000
0!
0%
#15624375000
1!
1%
b10 (
#15666040000
0!
b00000101 #
0%
b00000101 '
0*
#15707705000
1!
1%
b11 (
#15749370000
0!
0%
#15791035000
1!
1%
b100 (
#15832700000
0!
0%
#15874365000
1!
b00000010 #
1%
b00000010 '
b0 (
0)
#15916030000
0!
0%
#15957695000
1!
1%
b1 (
#15999360000
0!
0%
#16041025000
1!
1%
b10 (
#16082690000
0!
b00001010 #
0%
b00001010 '
1*
#16124355000
1!
1%
b11 (
#16166020000
0!
0%
#16207685000
1!
1%
b100 (
#16249350000
0!
0%
#16291015000
1!
b00001101 #
1%
b00001101 '
b0 (
1)
#16332680000
0!
0%
#16374345000
1!
1%
b1 (
#16416010000
0!
0%
#16457675000
1!
1%
b10 (
#16499340000
0!
b00000101 #
0%
b00000101 '
0*
#16541005000
1!
1%
b11 (
#16582670000
0!
0%
#16624335000
1!
1%
b100 (
#16666000000
0!
0%
#16707665000
1!
b00000010 #
1%
b00000010 '
b0 (
0)
#16749330000
0!
0%
#16790995000
1!
1%
b1 (
#16832660000
0!
0%
#16874325000
1!
1%
b10 (
#16915990000
0!
b00001010 #
0%
b00001010 '
1*
#16957655000
1!
1%
b11 (
#16999320000
0!
0%
#17040985000
1!
1%
b100 (
#17082650000
0!
0%
#17124315000
1!
b00001101 #
1%
b00001101 '
b0 (
1)
#17165980000
0!
0%
#17207645000
1!
1%
b1 (
#17249310000
0!
0%
#17290975000
1!
1%
b10 (
#17332640000
0!
b00000101 #
0%
b00000101 '
0*
#17374305000
1!
1%
b11 (
#17415970000
0!
0%
#17457635000
1!
1%
b100 (
#17499300000
0!
0%
#17540965000
1!
b00000010 #
1%
b00000010 '
b0 (
0)
#17582630000
0!
0%
#17624295000
1!
1%
b1 (
#17665960000
0!
0%
#17707625000
1!
1%
b10 (
#17749290000
0!
b00001010 #
0%
b00001010 '
1*
#17790955000
1!
1%
b11 (
#17832620000
0!
0%
#17874285000
1!
1%
b100 (
#17915950000
0!
0%
#17957615000
1!
b00001101 #
1%
b00001101 '
b0 (
1)
#17999280000
0!
0%
#18040945000
1!
1%
b1 (
#18082610000
0!
0%
#18124275000
1!
1%
b10 (
#18165940000
0!
b00000101 #
0%
b00000101 '
0*
#18207605000
1!
1%
b11 (
#18249270000
0!
0%
#18290935000
1!
1%
b100 (
#18332600000
0!
0%
#18374265000
1!
b00000010 #
1%
b00000010 '
b0 (
0)
#18415930000
0!
0%
#18457595000
1!
1%
b1 (
#18499260000
0!
0%
#18540925000
1!
1%
b10 (
#18582590000
0!
b00001010 #
0%
b00001010 '
1*
#18624255000
1!
1%
b11 (
#18665920000
0!
0%
#18707585000
1!
1%
b100 (
#18749250000
0!
0%
#18790915000
1!
b00001101 #
1%
b00001101 '
b0 (
1)
#18832580000
0!
0%
#18874245000
1!
1%
b1 (
#18915910000
0!
0%
#18957575000
1!
1%
b10 (
#18999240000
0!
b00000101 #
0%
b00000101 '
0*
#19040905000
1!
1%
b11 (
#19082570000
0!
0%
#19124235000
1!
1%
b100 (
#19165900000
0!
0%
#19207565000
1!
b00000010 #
1%
b00000010 '
b0 (
0)
#19249230000
0!
0%
#19290895000
1!
1%
b1 (
#19332560000
0!
0%
#19374225000
1!
1%
b10 (
#19415890000
0!
b00001010 #
0%
b00001010 '
1*
#19457555000
1!
1%
b11 (
#19499220000
0!
0%
#19540885000
1!
1%
b100 (
#19582550000
0!
0%
#19624215000
1!
b00001101 #
1%
b00001101 '
b0 (
1)
#19665880000
0!
0%
#19707545000
1!
1%
b1 (
#19749210000
0!
0%
#19790875000
1!
1%
b10 (
#19832540000
0!
b00000101 #
0%
b00000101 '
0*
#19874205000
1!
1%
b11 (
#19915870000
0!
0%
#19957535000
1!
1%
b100 (
#19999200000
0!
0%
#20040865000
1!
b00000010 #
1%
b00000010 '
b0 (
0)
#20082530000
0!
0%
#20124195000
1!
1%
b1 (
#20165860000
0!
0%
#20207525000
1!
1%
b10 (
#20249190000
0!
b00001010 #
0%
b00001010 '
1*
#20290855000
1!
1%
b11 (
#20332520000
0!
0%
#20374185000
1!
1%
b100 (
#20415850000
0!
0%
#20457515000
1!
b00001101 #
1%
b00001101 '
b0 (
1)
#20499180000
0!
0%
#20540845000
1!
1%
b1 (
#20582510000
0!
0%
#20624175000
1!
1%
b10 (
#20665840000
0!
b00000101 #
0%
b00000101 '
0*
#20707505000
1!
1%
b11 (
#20749170000
0!
0%
#20790835000
1!
1%
b100 (
#20832500000
0!
0%
#20874165000
1!
b00000010 #
1%
b00000010 '
b0 (
0)
#20915830000
0!
0%
#20957495000
1!
1%
b1 (
#20999160000
0!
0%
#21040825000
1!
1%
b10 (
#21082490000
0!
b00001010 #
0%
b00001010 '
1*
#21124155000
1!
1%
b11 (
#21165820000
0!
0%
#21207485000
1!
1%
b100 (
#21249150000
0!
0%
#21290815000
1!
b00001101 #
1%
b00001101 '
b0 (
1)
#21332480000
0!
0%
#21374145000
1!
1%
b1 (
#21415810000
0!
0%
#21457475000
1!
1%
b10 (
#21499140000
0!
b00000101 #
0%
b00000101 '
0*
#21540805000
1!
1%
b11 (
#21582470000
0!
0%
#21624135000
1!
1%
b100 (
#21665800000
0!
0%
#21707465000
1!
b00000010 #
1%
b00000010 '
b0 (
0)
#21749130000
0!
0%
#21790795000
1!
1%
b1 (
#21832460000
0!
0%
#21874125000
1!
1%
b10 (
#21915790000
0!
b00001010 #
0%
b00001010 '
1*
#21957455000
1!
1%
b11 (
#21999120000
0!
0%
#22040785000
1!
1%
b100 (
#22082450000
0!
0%
#22124115000
1!
b00001101 #
1%
b00001101 '
b0 (
1)
#22165780000
0!
0%
#22207445000
1!
1%
b1 (
#22249110000
0!
0%
#22290775000
1!
1%
b10 (
#22332440000
0!
b00000101 #
0%
b00000101 '
0*
#22374105000
1!
1%
b11 (
#22415770000
0!
0%
#22457435000
1!
1%
b100 (
#22499100000
0!
0%
#22540765000
1!
b00000010 #
1%
b00000010 '
b0 (
0)
#22582430000
0!
0%
#22624095000
1!
1%
b1 (
#22665760000
0!
0%
#22707425000
1!
1%
b10 (
#22749090000
0!
b00001010 #
0%
b00001010 '
1*
#22790755000
1!
1%
b11 (
#22832420000
0!
0%
#22874085000
1!
1%
b100 (
#22915750000
0!
0%
#22957415000
1!
b00001101 #
1%
b00001101 '
b0 (
1)
#22999080000
0!
0%
#23040745000
1!
1%
b1 (
#23082410000
0!
0%
#23124075000
1!
1%
b10 (
#23165740000
0!
b00000101 #
0%
b00000101 '
0*
#23207405000
1!
1%
b11 (
#23249070000
0!
0%
#23290735000
1!
1%
b100 (
#23332400000
0!
0%
#23374065000
1!
b00000010 #
1%
b00000010 '
b0 (
0)
#23415730000
0!
0%
#23457395000
1!
1%
b1 (
#23499060000
0!
0%
#23540725000
1!
1%
b10 (
#23582390000
0!
b00001010 #
0%
b00001010 '
1*
#23624055000
1!
1%
b11 (
#23665720000
0!
0%
#23707385000
1!
1%
b100 (
#23749050000
0!
0%
#23790715000
1!
b00001101 #
1%
b00001101 '
b0 (
1)
#23832380000
0!
0%
#23874045000
1!
1%
b1 (
#23915710000
0!
0%
#23957375000
1!
1%
b10 (
#23999040000
0!
b00000101 #
0%
b00000101 '
0*
#24040705000
1!
1%
b11 (
#24082370000
0!
0%
#24124035000
1!
1%
b100 (
#24165700000
0!
0%
#24207365000
1!
b00000010 #
1%
b00000010 '
b0 (
0)
#24249030000
0!
0%
#24290695000
1!
1%
b1 (
#24332360000
0!
0%
#24374025000
1!
1%
b10 (
#24415690000
0!
b00001010 #
0%
b00001010 '
1*
#24457355000
1!
1%
b11 (
#24499020000
0!
0%
#24540685000
1!
1%
b100 (
#24582350000
0!
0%
#24624015000
1!
b00001101 #
1%
b00001101 '
b0 (
1)
#24665680000
0!
0%
#24707345000
1!
1%
b1 (
#24749010000
0!
0%
#24790675000
1!
1%
b10 (
#24832340000
0!
b00000101 #
0%
b00000101 '
0*
#24874005000
1!
1%
b11 (
#24915670000
0!
0%
#24957335000
1!
1%
b100 (
#24999000000
0!
0%
#25040665000
1!
b00000010 #
1%
b00000010 '
b0 (
0)
#25082330000
0!
0%
#25123995000
1!
1%
b1 (
#25165660000
0!
0%
#25207325000
1!
1%
b10 (
#25248990000
0!
b00001010 #
0%
b00001010 '
1*
#25290655000
1!
1%
b11 (
#25332320000
0!
0%
#25373985000
1!
1%
b100 (
#25415650000
0!
0%
#25457315000
1!
b00001101 #
1%
b00001101 '
b0 (
1)
#25498980000
0!
0%
#25540645000
1!
1%
b1 (
#25582310000
0!
0%
#25623975000
1!
1%
b10 (
#25665640000
0!
b00000101 #
0%
b00000101 '
0*
#25707305000
1!
1%
b11 (
#25748970000
0!
0%
#25790635000
1!
1%
b100 (
#25832300000
0!
0%
#25873965000
1!
b00000010 #
1%
b00000010 '
b0 (
0)
#25915630000
0!
0%
#25957295000
1!
1%
b1 (
#25998960000
0!
0%
